dash_tools/__init__.py
dash_tools/backup_handler.py
dash_tools/batch_encoder.py
dash_tools/cea608.py
dash_tools/cea608tottml_multi_region.py
dash_tools/cea608towebvtt.py
dash_tools/cea708.py
dash_tools/changebrands.py
dash_tools/changelmsg.py
dash_tools/changetfdt.py
dash_tools/fix_sync_sample_flags.py
dash_tools/initcleaner.py
dash_tools/livedownloader.py
dash_tools/mediacleaner.py
dash_tools/mp4.py
dash_tools/mp4_parse.py
dash_tools/mp4filter.py
dash_tools/mpdparser.py
dash_tools/ondemand_add_subs.py
dash_tools/ondemand_creator.py
dash_tools/ondemand_verifier.py
dash_tools/parse_mss_segment.py
dash_tools/restore_from_bup.py
dash_tools/sample_tables.py
dash_tools/scc.py
dash_tools/scc_ttml_multi_region.py
dash_tools/sccgen.py
dash_tools/shift_composition_time.py
dash_tools/stppfixer.py
dash_tools/structops.py
dash_tools/track_data_extractor.py
dash_tools/track_resegmenter.py
dash_tools/trick_mode_segment_creator.py
dash_tools/ts.py
dash_mediatools-0.9.0.dist-info/LICENSE.txt
dash_mediatools-0.9.0.dist-info/METADATA
dash_mediatools-0.9.0.dist-info/WHEEL
dash_mediatools-0.9.0.dist-info/entry_points.txt
dash_mediatools-0.9.0.dist-info/top_level.txt
dash_mediatools-0.9.0.dist-info/RECORD
