Metadata-Version: 2.1
Name: dash-mediatools
Version: 0.9.0
Summary: Tools for MPEG-DASH media creation and analysis
Home-page: https://github.com/Dash-Industry-Forum/media-tools/tree/master/python
Author: Torbjorn Einarsson
Author-email: torbjorn.einarsson@edgeware.tv
License: BSD
Keywords: MPEG-DASH mp4 ttml mpeg2-ts
Platform: UNKNOWN
Classifier: Development Status :: 4 - Beta
Classifier: Intended Audience :: Developers
Classifier: Topic :: Multimedia :: Video :: Conversion
Classifier: License :: OSI Approved :: BSD License
Classifier: Programming Language :: Python :: 2
Classifier: Programming Language :: Python :: 2.7
Requires-Python: == 2.7.*
